dammy/__init__.py
dammy/core.py
dammy/db.py
dammy/exceptions.py
dammy/functions.py
dammy/iterator.py
dammy/stdlib.py
dammy/data/car_models.json
dammy/data/countries.json
dammy/data/names.json
dammy-1.1.0.dist-info/LICENSE
dammy-1.1.0.dist-info/METADATA
dammy-1.1.0.dist-info/WHEEL
dammy-1.1.0.dist-info/top_level.txt
dammy-1.1.0.dist-info/RECORD
