Metadata-Version: 2.1
Name: dammy
Version: 1.1.0
Summary: Generate fake data for any purpose
Home-page: https://github.com/ibonn/dammy
Author: Ibon
Author-email: ibonescartin@gmail.com
License: GPL-3.0
Download-URL: https://pypi.org/project/dammy/
Project-URL: Documentation, https://readthedocs.org/projects/dammy/
Project-URL: Source Code, https://github.com/ibonn/dammy
Keywords: dummy-data,fake,mock,database,sql,dummy,test,data,population
Platform: UNKNOWN
Classifier: Intended Audience :: Developers
Classifier: License :: OSI Approved :: GNU General Public License v3 (GPLv3)
Classifier: Programming Language :: Python
Classifier: Programming Language :: Python :: 3
Classifier: Programming Language :: Python :: Implementation :: CPython
Classifier: Programming Language :: Python :: Implementation :: PyPy
Classifier: Topic :: Database
Classifier: Topic :: Software Development :: Testing
Classifier: Topic :: Software Development :: Testing :: Mocking
Classifier: Topic :: Utilities
